Workbook

Sheet Overview
A1: Agentic Use Case Portfolio — Overview
A2: All counts are live formulas over the Use Case Mapping sheet.
A4: By Archetype
A5: Archetype | B5: Primary | C5: Secondary
A6: A1 Extract & Validate | B6: =COUNTIF('Use Case Mapping'!$D$5:$D$29,A6) -> 5 | C6: =COUNTIF('Use Case Mapping'!$E$5:$E$29,A6) -> 5
A7: A2 Compare & Flag | B7: =COUNTIF('Use Case Mapping'!$D$5:$D$29,A7) -> 5 | C7: =COUNTIF('Use Case Mapping'!$E$5:$E$29,A7) -> 4
A8: A3 Screen & Build Universe | B8: =COUNTIF('Use Case Mapping'!$D$5:$D$29,A8) -> 2 | C8: =COUNTIF('Use Case Mapping'!$E$5:$E$29,A8) -> 0
A9: A4 Draft with Evidence | B9: =COUNTIF('Use Case Mapping'!$D$5:$D$29,A9) -> 7 | C9: =COUNTIF('Use Case Mapping'!$E$5:$E$29,A9) -> 5
A10: A5 Answer with Citations | B10: =COUNTIF('Use Case Mapping'!$D$5:$D$29,A10) -> 4 | C10: =COUNTIF('Use Case Mapping'!$E$5:$E$29,A10) -> 1
A11: A6 Synthesize & Remember | B11: =COUNTIF('Use Case Mapping'!$D$5:$D$29,A11) -> 2 | C11: =COUNTIF('Use Case Mapping'!$E$5:$E$29,A11) -> 1
A12: Total | B12: =SUM(B6:B11) -> 25 | C12: =SUM(C6:C11) -> 16
A15: By Risk Tier | D15: By Wave
A16: Tier | B16: Count | D16: Wave | E16: Count
A17: Tier 1 | B17: =COUNTIF('Use Case Mapping'!$G$5:$G$29,A17) -> 5 | D17: W1 | E17: =COUNTIF('Use Case Mapping'!$I$5:$I$29,D17) -> 4
A18: Tier 2 | B18: =COUNTIF('Use Case Mapping'!$G$5:$G$29,A18) -> 13 | D18: W2 | E18: =COUNTIF('Use Case Mapping'!$I$5:$I$29,D18) -> 11
A19: Tier 3 | B19: =COUNTIF('Use Case Mapping'!$G$5:$G$29,A19) -> 7 | D19: W3 | E19: =COUNTIF('Use Case Mapping'!$I$5:$I$29,D19) -> 8
D20: W4 | E20: =COUNTIF('Use Case Mapping'!$I$5:$I$29,D20) -> 2
A22: Reading guide
A23: Use Case Mapping - the master table: filter by LOB, archetype, tier, or wave.
A24: Archetypes - the six reusable stacks with implementation blueprints (use-case counts are live).
A25: Risk Tiers - tier definitions, autonomy ceilings, and required control sets.
A26: Roadmap - four delivery waves with entry/exit criteria.
A27: Platform Services - the build-once shared layer each archetype consumes.

Sheet Use Case Mapping
A1: Use Case → Archetype → Pattern Mapping
A2: 25 use cases, 6 reusable archetypes. Filter, sort, and re-tier as the portfolio evolves.
A4: # | B4: LOB | C4: Use Case | D4: Primary Archetype | E4: Secondary Archetype | F4: Pattern Stack | G4: Risk Tier | H4: Autonomy Ceiling | I4: Wave | J4: Data Sensitivity | K4: Output Type | L4: Key Controls | M4: Implementation Notes
A5: 1 | B5: CAB | C5: Term sheet-to-booking translator | D5: A1 Extract & Validate | E5: A2 Compare & Flag | F5: Prompt chaining + structured output + field confidence + maker-checker | G5: Tier 1 | H5: Propose-only | I5: W4 | J5: Confidential (deal terms) | K5: Booking instructions + completeness checklist (pending) | L5: Maker-checker before funding; schema per product type; completeness rules deterministic; full evidence trail | M5: Validate against product-type checklists in code, not the model; nothing reaches Ops as final until checked; pilot on one product type
A6: 2 | B6: CAB | C6: Financial spreading assistant | D6: A2 Compare & Flag | E6: A1 Extract & Validate | F6: LLM extraction + deterministic ratio engine + LLM variance commentary | G6: Tier 2 | H6: Execute w/ approval | I6: W2 | J6: Confidential (borrower financials) | K6: Spread + covenant headroom + draft commentary | L6: Ratios and headroom computed in code; commentary cites the computed diff; analyst signs the spread | M6: The number is never model-generated: LLM maps statement lines to the template, engine computes, LLM narrates
A7: 3 | B7: CAB | C7: Collections prioritization engine | D7: A2 Compare & Flag | E7: A4 Draft with Evidence | F7: Deterministic/classical scoring core + LLM outreach drafting + playbook selection | G7: Tier 2 | H7: Execute w/ approval | I7: W3 | J7: Confidential (client PII) | K7: Ranked queue + draft outreach scripts + follow-up schedule | L7: Scoring model under MRM validation; outreach from approved script playbook; fair-treatment review; human sends | M7: Recovery-likelihood score is a classical model, not an LLM; LLM personalizes from approved templates only
A8: 4 | B8: Credit Alternatives | C8: Virtual assistant - investment management | D8: A5 Answer with Citations | F8: RAG + hybrid retrieval + entitlement filters + abstention | G8: Tier 2 | H8: Execute w/ approval | I8: W2 | J8: Confidential (private transaction terms) | K8: Cited chat answers over deal docs | L8: Deal-level entitlements enforced in the index query; citation-or-silence; abstain below retrieval threshold | M8: Access boundaries are per-deal/per-LP; never post-filter; log every retrieval for audit
A9: 5 | B9: Credit Alternatives | C9: Private credit covenant monitor | D9: A1 Extract & Validate | E9: A2 Compare & Flag | F9: Doc extraction (covenants/baskets/triggers) + deterministic monitoring engine + exceptions dashboard + draft outreach | G9: Tier 2 | H9: Execute w/ approval | I9: W3 | J9: Confidential (credit docs) | K9: Covenant register + exceptions dashboard + draft sponsor outreach | L9: Extracted covenant terms human-verified once at setup; breach math in code; outreach drafts reviewed before send | M9: Two-phase design: extraction is one-time-per-doc with HITL sign-off; monitoring then runs deterministically against borrower reporting
A10: 6 | B10: Credit Alternatives | C10: Automated monitoring (insurer transaction tagging) | D10: A1 Extract & Validate | F10: Structured output + field confidence + pending-state writes | G10: Tier 2 | H10: Execute w/ approval | I10: W2 | J10: Confidential | K10: Tagged records in centralized DB (pending until sampled) | L10: Field-level confidence; low-confidence to human queue; sampled QC on auto-accepted records; DB writes via gated service | M10: Start at 100% review, ratchet down to sampling as eval evidence accumulates
A11: 7 | B11: FI | C11: Irish ADR dividend tax reclaim documentation | D11: A1 Extract & Validate | E11: A4 Draft with Evidence | F11: Extraction + template filling + deterministic eligibility/amount rules + maker-checker | G11: Tier 1 | H11: Propose-only | I11: W3 | J11: Confidential (client tax data) | K11: Reclaim filing packs (pending) | L11: Reclaim amounts and eligibility computed in code; tax authority format rules as validators; checker signs every filing | M11: Tax filings are Tier 1: the model assembles and fills, deterministic rules compute, a human files
A12: 8 | B12: FI | C12: N-2 Universe Builder & Structured Credit Screener | D12: A3 Screen & Build Universe | F12: Scheduled batch + deterministic pre-filters + LLM classification + evidence links | G12: Tier 3 | H12: Execute w/ sampled review | I12: W2 | J12: Public (filings) | K12: Evidence-linked fund universe subset | L12: Every include/exclude decision logged with the marker that drove it; sampled review of exclusions; rerun reproducibility | M12: Cheap deterministic filters first (form type, keywords), LLM only on survivors; exclusion errors are the silent risk - sample them
A13: 9 | B13: Funds | C13: K-1 drafting | D13: A4 Draft with Evidence | E13: A1 Extract & Validate | F13: Template-conditioned drafting + deterministic figure sourcing + reflection critic + maker-checker | G13: Tier 1 | H13: Propose-only | I13: W3 | J13: Confidential (investor tax data) | K13: Draft K-1s (pending) | L13: All figures sourced from systems of record, never generated; critic checks template conformance; tax team owns release | M13: The model drafts narrative/format around system-sourced numbers; any figure the model produced rather than pulled is a defect
A14: 10 | B14: Funds | C14: Investor query copilot | D14: A5 Answer with Citations | E14: A4 Draft with Evidence | F14: RAG over fund docs/notices/FAQs + citations + draft response generation | G14: Tier 2 | H14: Execute w/ approval | I14: W1 | J14: Confidential (fund/LP docs) | K14: Draft investor responses with citations | L14: Fund-level entitlements in retrieval; citation-or-silence; IR team reviews and sends; abstain on performance/advice questions | M14: Wave 1 anchor: high volume, drafts only, human always sends - ideal trust-builder with real controls
A15: 11 | B15: IRG | C15: Manager KPI benchmarker | D15: A2 Compare & Flag | E15: A1 Extract & Validate | F15: Extraction from filings/tearsheets + deterministic standardization & peer stats + outlier flagging | G15: Tier 3 | H15: Execute w/ sampled review | I15: W2 | J15: Internal/vendor data | K15: Standardized KPI table + outliers + ODD question list | L15: KPI normalization rules in code; outlier thresholds configurable; extraction spans linked for verification | M15: Benchmark math is deterministic; the LLM maps heterogeneous disclosures into the standard schema and drafts ODD questions
A16: 12 | B16: IRG | C16: CPMS search enhancement | D16: A5 Answer with Citations | F16: Hybrid retrieval over internal IRG database + query rewriting | G16: Tier 3 | H16: Execute w/ sampled review | I16: W1 | J16: Internal | K16: Relevant data pulls / ranked results | L16: Read-only access; result provenance shown; relevance feedback captured | M16: Pure retrieval quality play: hybrid search + reranking over CPMS; lowest-risk entry point for IRG
A17: 13 | B17: MFO | C17: Daily deposit/withdrawal reporting & next steps | D17: A4 Draft with Evidence | E17: A2 Compare & Flag | F17: Deterministic data aggregation + templated summary drafting + playbook-constrained recommendations | G17: Tier 2 | H17: Execute w/ approval | I17: W2 | J17: Confidential (client PII) | K17: Daily report + recommended next steps (from playbook) | L17: Figures from systems of record; recommendations selected from approved playbook, never free-form advice; advisor reviews | M17: The riskiest element is 'recommendations' - constrain to a pre-approved action playbook with selection rationale
A18: 14 | B18: MFO | C18: Charitable giving optimizer | D18: A4 Draft with Evidence | E18: A2 Compare & Flag | F18: Deterministic tax-benefit calculators + LLM outline drafting + reflection critic | G18: Tier 2 | H18: Execute w/ approval | I18: W3 | J18: Confidential (client tax/positions) | K18: Giving outline + tax benefit summary (draft) | L18: Tax math in validated calculators; outputs framed as scenarios for advisor review, not advice; suitability stays human | M18: Lot selection and benefit math are computation; the model explains and structures - it never invents a tax number
A19: 15 | B19: MFO | C19: Relationship memory & interaction summarization | D19: A6 Synthesize & Remember | F19: CDC ingestion (CRM/email/notes) + per-client context store + scheduled re-synthesis + pinned facts | G19: Tier 2 | H19: Execute w/ sampled review | I19: W3 | J19: Confidential (client PII) | K19: Continuously updated relationship summary | L19: Highest data classification; retention & deletion propagate to the store; write policy excludes secrets; access mirrors CRM entitlements | M19: Pinned-facts pattern so sensitivities and standing instructions never compact away; scheduled synthesis beats on-demand for cost and consistency
A20: 16 | B20: Ops / Admin | C20: Policy-to-procedure conformance checker | D20: A2 Compare & Flag | E20: A4 Draft with Evidence | F20: Clause-level extraction + deterministic diff/coverage mapping + redline drafting with trace | G20: Tier 2 | H20: Execute w/ approval | I20: W2 | J20: Internal (policies/SOPs) | K20: Gap report + draft redlines with traceability | L20: Coverage mapping rules explicit; every flagged gap cites both policy and SOP spans; owners accept/reject redlines | M20: Treat as requirements-coverage analysis: deterministic mapping of obligations to procedure steps, LLM drafts the redline text
A21: 17 | B21: Ops / Admin | C21: Meeting notetaker / transcription | D21: A4 Draft with Evidence | F21: Transcription + templated summary + action-item extraction | G21: Tier 3 | H21: Execute w/ sampled review | I21: W1 | J21: Internal | K21: Draft meeting notes & action items | L21: Drafts clearly labeled; participants edit; retention policy on recordings/transcripts; consent per policy | M21: Wave 1 trust-builder; the governance question is recording consent and transcript retention, not model risk
A22: 18 | B22: Ops / Admin | C22: SDLC project management documentation | D22: A4 Draft with Evidence | F22: Template-conditioned drafting over project artifacts + reflection critic | G22: Tier 3 | H22: Execute w/ sampled review | I22: W1 | J22: Internal | K22: Draft roadmaps, requirements, procedures | L22: Drafts only; document owners review; version control through normal SDLC; templates as skeletons | M22: ~15 FTE leverage today: highest-volume internal win; chain per-section, never one mega-prompt per document
A23: 19 | B23: PE | C23: IC memo drafting (exec summary, risks, VCP) | D23: A4 Draft with Evidence | F23: RAG over deal room + template-conditioned sections + reflection critic + assertion-level evidence links | G23: Tier 2 | H23: Execute w/ approval | I23: W2 | J23: Confidential (deal data) | K23: First-draft IC memo sections with evidence trace | L23: Every assertion links to underlying evidence; critic scores traceability & template conformance; deal team owns the memo | M23: Section-by-section chaining against the memo template; risk matrix entries each carry their source citation
A24: 20 | B24: PE | C24: Industry & competitive landscape sections | D24: A4 Draft with Evidence | E24: A6 Synthesize & Remember | F24: RAG over sourced market data + footnoted drafting + template tone conditioning | G24: Tier 3 | H24: Execute w/ sampled review | I24: W2 | J24: Internal/vendor data | K24: Drafted market & competitive sections with footnotes | L24: Approved data sources only; every figure footnoted; vendor licensing respected in retrieval corpus | M24: Pair with the research aggregation service (A6) as its feed; footnote discipline is the eval criterion
A25: 21 | B25: Public Equities | C25: Client review & investment survey harmonization | D25: A1 Extract & Validate | F25: Per-document extraction schemas + field confidence + harmonized summary generation | G25: Tier 2 | H25: Execute w/ approval | I25: W2 | J25: Confidential (client holdings) | K25: Harmonized summaries + analyst review flags | L25: Constraint/exposure extraction verified above threshold only; changes-requiring-review explicitly flagged; analyst confirms | M25: Bespoke inbound formats are the challenge: schema-per-source-type with a fallback human queue for unrecognized formats
A26: 22 | B26: Public Equities | C26: Public data & research aggregation | D26: A6 Synthesize & Remember | E26: A5 Answer with Citations | F26: Continuous ingestion (news/filings/transcripts/sentiment) + per-ticker store + scheduled briefs | G26: Tier 3 | H26: Execute w/ sampled review | I26: W2 | J26: Public/vendor data | K26: Analyst-ready briefs with source links | L26: Source whitelist (licensing & quality); sentiment clearly labeled as signal not fact; brief provenance per item | M26: Per-ticker context store with freshness SLAs; vendor content licensing reviewed before it enters the corpus
A27: 23 | B27: Trust Co. | C27: Fee schedule compliance checker | D27: A2 Compare & Flag | E27: A1 Extract & Validate | F27: Fee terms extraction (one-time, verified) + deterministic assessment comparison + deviation memos | G27: Tier 2 | H27: Execute w/ approval | I27: W3 | J27: Confidential (client fee terms) | K27: Deviation flags + draft adjustment memos | L27: Fee math entirely in code; extracted schedules human-verified at setup; adjustments through maker-checker | M27: Same two-phase shape as covenant monitor: verified extraction once, deterministic comparison forever
A28: 24 | B28: Trust Co. | C28: Trust synoptic (docs, state law, side letters) | D28: A5 Answer with Citations | E28: A4 Draft with Evidence | F28: Multi-corpus RAG (trust docs + state law + side letters + transactions) + verifier chain on every conclusion | G28: Tier 1 | H28: Propose-only | I28: W4 | J28: Confidential (fiduciary) | K28: Analysis briefs for counsel/officer review | L28: Verifier confirms every permissibility statement against source spans; output framed as analysis, never a ruling; counsel disposes | M28: The heavyweight: needs mature multi-corpus retrieval + verifier chain; fiduciary conclusions stay with humans permanently
A29: 25 | B29: Trust Co. | C29: Fiduciary calendar & deadline manager | D29: A3 Screen & Build Universe | E29: A1 Extract & Validate | F29: Dual-sourced deadlines (statutory rules table + document extraction) + discrepancy flagging + evidence capture | G29: Tier 1 | H29: Propose-only | I29: W3 | J29: Confidential (fiduciary) | K29: Deadline calendar with audit evidence | L29: Statutory deadlines from a maintained rules table; document-driven dates extracted and human-confirmed; discrepancies flag, never auto-resolve | M29: A missed statutory deadline is a fiduciary breach: the rules table is the system of record, extraction is the cross-check

Sheet Archetypes
A1: The Six Archetypes
A2: Build these six stacks once on shared platform services; every use case is a configuration of one (sometimes two).
A4: ID | B4: Archetype | C4: Pattern Stack | D4: Implementation Blueprint | E4: Key Design Rule | F4: # Primary | G4: # Secondary
A5: A1 | B5: Extract & Validate | C5: Prompt chaining + structured output + field-level confidence + HITL queue | D5: Per-document-type extraction schemas; every field carries confidence and a source span; below-threshold fields route to a human queue with the span highlighted; results land as PENDING and reach the system of record only through a gated write. | E5: Extracted data is never final data. Start at 100% review and ratchet to sampling only on eval evidence. | F5: =COUNTIF('Use Case Mapping'!$D$5:$D$29,"A1 *") -> 5 | G5: =COUNTIF('Use Case Mapping'!$E$5:$E$29,"A1 *") -> 5
A6: A2 | B6: Compare & Flag | C6: LLM extraction + deterministic comparison engine + LLM narrative + exceptions dashboard | D6: The LLM maps unstructured inputs into structured form on both sides; a deterministic engine computes the diff, ratio, headroom, or coverage; the LLM drafts the variance commentary or redline citing the computed result. | E6: The number that flags a breach is never model-generated. Deterministic core, probabilistic edges. | F6: =COUNTIF('Use Case Mapping'!$D$5:$D$29,"A2 *") -> 5 | G6: =COUNTIF('Use Case Mapping'!$E$5:$E$29,"A2 *") -> 4
A7: A3 | B7: Screen & Build Universe | C7: Scheduled batch + deterministic pre-filters + LLM classification + evidence links | D7: Airflow-native batch: pull the corpus, apply cheap deterministic filters first, run LLM classification only on survivors, and log every include/exclude decision with the marker that drove it. Reruns must reproduce. | E7: Exclusion errors are silent - sample and review what was screened OUT, not just what got through. | F7: =COUNTIF('Use Case Mapping'!$D$5:$D$29,"A3 *") -> 2 | G7: =COUNTIF('Use Case Mapping'!$E$5:$E$29,"A3 *") -> 0
A8: A4 | B8: Draft with Evidence | C8: RAG + template conditioning + reflection critic + HITL ownership | D8: Retrieval restricted to approved sources; templates as structured skeletons filled section-by-section (chained, never one mega-prompt); a critic scores each draft against a per-document-type rubric; assertions link to evidence. | E8: Output is always a draft a named human edits and owns. Recommendations come from approved playbooks, never free-form. | F8: =COUNTIF('Use Case Mapping'!$D$5:$D$29,"A4 *") -> 7 | G8: =COUNTIF('Use Case Mapping'!$E$5:$E$29,"A4 *") -> 5
A9: A5 | B9: Answer with Citations | C9: RAG + hybrid retrieval + entitlement filters + citation-or-silence + abstention | D9: Entitlements enforced inside the index query (deal-level, fund-level, client-level) - never post-filtered; hybrid retrieval with reranking; every claim cites a source span; below-threshold retrieval abstains honestly. | E9: A leaked context cannot be un-shown to the model: entitlement filtering happens at retrieval, structurally. | F9: =COUNTIF('Use Case Mapping'!$D$5:$D$29,"A5 *") -> 4 | G9: =COUNTIF('Use Case Mapping'!$E$5:$E$29,"A5 *") -> 1
A10: A6 | B10: Synthesize & Remember | C10: Continuous/CDC ingestion + per-entity context store + scheduled re-synthesis + pinned facts | D10: CDC-style ingestion from each source into a per-client or per-ticker store; scheduled re-synthesis (cost + consistency) rather than on-demand; pinned facts preserve sensitivities and standing instructions through compaction. | E10: The memory store inherits the highest classification of anything in it; retention and deletion must propagate to it. | F10: =COUNTIF('Use Case Mapping'!$D$5:$D$29,"A6 *") -> 2 | G10: =COUNTIF('Use Case Mapping'!$E$5:$E$29,"A6 *") -> 1

Sheet Risk Tiers
A1: Risk Tiers & Control Sets
A2: The tier decides autonomy and controls. Tier assignment is reviewed at intake and re-confirmed at every material change.
A4: Tier | B4: Definition | C4: Autonomy Ceiling | D4: Required Controls | E4: # Use Cases
A5: Tier 1 | B5: Touches client money, tax/regulatory filings, funding instructions, or fiduciary conclusions. A wrong output has direct legal, financial, or fiduciary consequence. | C5: Propose-only, permanently. Promotion out of propose-only is an MRM event requiring independent validation - it is never a product decision. | D5: Maker-checker on every output; deterministic computation of all figures; full evidence ledger; independent model validation; immutable WORM audit trail; rehearsed kill switch; shadow period before launch. | E5: =COUNTIF('Use Case Mapping'!$G$5:$G$29,"Tier 1") -> 5
A6: Tier 2 | B6: Client-facing content, client PII, regulated monitoring, or inputs to client decisions. Errors are damaging but reviewable before harm. | C6: Execute with approval: a named human reviews and releases every output (or every consequential output). | D6: HITL approval queue with evidence display; entitlement-filtered retrieval; golden-set CI gates; output guardrails + PII scan; full trace; quarterly eval review. | E6: =COUNTIF('Use Case Mapping'!$G$5:$G$29,"Tier 2") -> 13
A7: Tier 3 | B7: Internal productivity and research with reversible outputs reviewed in normal workflow. | C7: Execute with sampled review: outputs flow, a defined sample is quality-reviewed, and rates are monitored. | D7: Sampled QC with defined rates; standard guardrails and tracing; cost budgets; drift monitoring; normal SDLC ownership. | E7: =COUNTIF('Use Case Mapping'!$G$5:$G$29,"Tier 3") -> 7

Sheet Roadmap
A1: Sequencing Roadmap
A2: Capability compounds: each wave's exit criteria are the next wave's foundation.
A4: Wave | B4: Timeline | C4: Theme | D4: # Use Cases | E4: Entry Criteria | F4: Exit Criteria
A5: W1 | B5: 0-3 months | C5: Internal trust-builders: drafts-only, high volume, low blast radius (notetaker, SDLC docs, investor copilot, CPMS search). | D5: =COUNTIF('Use Case Mapping'!$I$5:$I$29,"W1") -> 4 | E5: Gateway MVP + audit store + eval harness live; risk-tiering intake operating. | F5: Measured lift vs. baseline on each; guardrails tuned on real traffic; user adoption and override rates reported.
A6: W2 | B6: 3-6 months | C6: Evidence-drafting and screening at scale: deterministic cores proven (spreading, N-2 screener, IC memos, conformance checker, harmonization, daily reporting, tagging, KPI benchmarker, research aggregation, landscape sections, VA-IM). | D6: =COUNTIF('Use Case Mapping'!$I$5:$I$29,"W2") -> 11 | E6: A1/A2/A3/A4 archetype services productized; HITL queue service live; per-use-case golden sets. | F6: Second use case in an archetype ships in weeks; deterministic-core pattern validated by reconciliation; cost per outcome tracked.
A7: W3 | B7: 6-12 months | C7: Regulated monitoring & client-sensitive systems (covenant monitor, fee compliance, collections, ADR reclaims, K-1 drafting, charitable giving, relationship memory, fiduciary calendar). | D7: =COUNTIF('Use Case Mapping'!$I$5:$I$29,"W3") -> 8 | E7: MRM validation process exercised; maker-checker tooling mature; memory-store governance (retention/deletion) approved. | F7: Zero unreviewed Tier 1/2 outputs released; examiner-ready evidence pack produced for at least one system; incident runbook rehearsed.
A8: W4 | B8: 12+ months | C8: Fiduciary & funding-critical (trust synoptic, term sheet-to-booking): mature platform, permanent propose-only posture. | D8: =COUNTIF('Use Case Mapping'!$I$5:$I$29,"W4") -> 2 | E8: Multi-corpus retrieval + verifier chains proven; W3 systems stable through at least one audit/exam cycle. | F8: Counsel/Ops adoption with documented time savings; verifier precision evidenced; standing MRM revalidation cadence.

Sheet Platform Services
A1: Shared Platform Services
A2: Build once, consumed by every archetype. The platform is why use case #7 ships in weeks.
A4: Service | B4: What it provides | C4: Consumed by archetypes | D4: Build wave
A5: Model gateway | B5: Routing, fallback, quotas/budgets, data-class topology enforcement, provider abstraction, kill switch per use case. | C5: All | D5: W1
A6: Audit & trace store | B6: Immutable (WORM-style) capture of prompts, retrievals, tool calls, model versions, approvals; replayable per examiner request. | C6: All | D6: W1
A7: Eval harness | B7: Golden-set management, rubric scoring, LLM-judge calibration, trajectory evals, CI gates. | C7: All | D7: W1
A8: Document ingestion & extraction | B8: Parsing, chunking, per-type extraction schemas, field-level confidence scoring. | C8: A1, A2, A3 | D8: W2
A9: Entitlement-aware RAG service | B9: Hybrid retrieval + reranking with deal/fund/client entitlements enforced in the index query; citation spans. | C9: A4, A5, A6 | D9: W1-W2
A10: Deterministic comparison engine | B10: Ratio, headroom, fee, coverage, and deadline computation as validated code with versioned rule sets. | C10: A2, A3 | D10: W2
A11: Template drafting service | B11: Skeleton-based section drafting, tone conditioning, reflection critic with per-doc-type rubrics. | C11: A4 | D11: W2
A12: HITL queue & maker-checker | B12: Approval queues displaying the evidence ledger; identity-logged sign-off; auto-expiry; sampling mode. | C12: All (mandatory A1/Tier 1-2) | D12: W2
A13: Batch scheduler (Airflow) | B13: Scheduled pipelines for screening, monitoring runs, and re-synthesis; freshness SLAs; loud failure. | C13: A2, A3, A6 | D13: Existing
A14: Entity context / memory store | B14: Per-client/per-ticker stores with pinned facts, retention & deletion propagation, classification-inherited access. | C14: A6 (A4/A5 read) | D14: W3
